{
  "minecraft:recipes/tools/fishing_rod": {
    "criteria": {
      "has_string": "2022-09-30 04:14:21 -0600"
    },
    "done": true
  },
  "minecraft:recipes/tools/wooden_axe": {
    "criteria": {
      "has_stick": "2022-09-27 15:00:37 -0600"
    },
    "done": true
  },
  "minecraft:recipes/building_blocks/magenta_concrete_powder": {
    "criteria": {
      "has_sand": "2022-09-28 03:49:33 -0600"
    },
    "done": true
  },
  "minecraft:recipes/combat/iron_sword": {
    "criteria": {
      "has_iron_ingot": "2022-09-27 11:50:25 -0600"
    },
    "done": true
  },
  "minecraft:recipes/misc/magenta_dye_from_lilac": {
    "criteria": {
      "has_lilac": "2022-09-30 04:53:25 -0600"
    },
    "done": true
  },
  "minecraft:recipes/misc/paper": {
    "criteria": {
      "has_reeds": "2022-09-30 04:53:26 -0600"
    },
    "done": true
  },
  "minecraft:recipes/misc/light_blue_dye_from_blue_orchid": {
    "criteria": {
      "has_blue_orchid": "2022-09-30 04:53:27 -0600"
    },
    "done": true
  },
  "minecraft:recipes/misc/pink_dye_from_peony": {
    "criteria": {
      "has_peony": "2022-09-30 04:53:25 -0600"
    },
    "done": true
  },
  "minecraft:recipes/combat/golden_chestplate": {
    "criteria": {
      "has_gold_ingot": "2022-09-30 04:52:58 -0600"
    },
    "done": true
  },
  "minecraft:recipes/food/cooked_salmon_from_smoking": {
    "criteria": {
      "has_salmon": "2022-09-27 11:33:33 -0600"
    },
    "done": true
  },
  "minecraft:recipes/decorations/loom": {
    "criteria": {
      "has_string": "2022-09-30 04:14:21 -0600"
    },
    "done": true
  },
  "minecraft:recipes/misc/light_gray_dye_from_white_tulip": {
    "criteria": {
      "has_white_tulip": "2022-09-30 04:54:15 -0600"
    },
    "done": true
  },
  "minecraft:recipes/building_blocks/lime_concrete_powder": {
    "criteria": {
      "has_sand": "2022-09-28 03:49:33 -0600"
    },
    "done": true
  },
  "minecraft:recipes/tools/diamond_axe": {
    "criteria": {
      "has_diamond": "2022-09-27 11:33:33 -0600"
    },
    "done": true
  },
  "minecraft:recipes/transportation/furnace_minecart": {
    "criteria": {
      "has_minecart": "2022-09-30 04:14:17 -0600"
    },
    "done": true
  },
  "minecraft:recipes/tools/iron_pickaxe": {
    "criteria": {
      "has_iron_ingot": "2022-09-27 11:50:25 -0600"
    },
    "done": true
  },
  "minecraft:recipes/building_blocks/yellow_concrete_powder": {
    "criteria": {
      "has_sand": "2022-09-28 03:49:33 -0600"
    },
    "done": true
  },
  "minecraft:recipes/misc/green_dye": {
    "criteria": {
      "has_cactus": "2022-09-30 04:53:25 -0600"
    },
    "done": true
  },
  "minecraft:recipes/combat/leather_helmet": {
    "criteria": {
      "has_leather": "2022-09-27 15:31:59 -0600"
    },
    "done": true
  },
  "minecraft:recipes/misc/pumpkin_seeds": {
    "criteria": {
      "has_pumpkin": "2022-09-30 04:53:26 -0600"
    },
    "done": true
  },
  "minecraft:recipes/misc/blue_dye_from_cornflower": {
    "criteria": {
      "has_cornflower": "2022-09-30 04:54:15 -0600"
    },
    "done": true
  },
  "minecraft:recipes/redstone/slime_block": {
    "criteria": {
      "has_slime_ball": "2022-09-30 04:54:57 -0600"
    },
    "done": true
  },
  "minecraft:recipes/building_blocks/dark_prismarine": {
    "criteria": {
      "has_prismarine_shard": "2022-09-30 04:54:58 -0600"
    },
    "done": true
  },
  "minecraft:recipes/decorations/campfire": {
    "criteria": {
      "has_stick": "2022-09-27 15:00:37 -0600"
    },
    "done": true
  },
  "minecraft:recipes/decorations/candle": {
    "criteria": {
      "has_string": "2022-09-30 04:14:21 -0600"
    },
    "done": true
  },
  "minecraft:recipes/tools/golden_hoe": {
    "criteria": {
      "has_gold_ingot": "2022-09-30 04:52:58 -0600"
    },
    "done": true
  },
  "minecraft:recipes/building_blocks/copper_block": {
    "criteria": {
      "has_copper_ingot": "2022-09-28 03:39:35 -0600"
    },
    "done": true
  },
  "minecraft:recipes/decorations/scaffolding": {
    "criteria": {
      "has_bamboo": "2022-09-30 04:53:25 -0600"
    },
    "done": true
  },
  "minecraft:recipes/decorations/ladder": {
    "criteria": {
      "has_stick": "2022-09-27 15:00:37 -0600"
    },
    "done": true
  },
  "minecraft:recipes/misc/iron_nugget": {
    "criteria": {
      "has_iron_ingot": "2022-09-27 11:50:25 -0600"
    },
    "done": true
  },
  "minecraft:recipes/decorations/chest": {
    "criteria": {
      "has_lots_of_items": "2022-09-28 05:22:10 -0600"
    },
    "done": true
  },
  "minecraft:recipes/transportation/hopper_minecart": {
    "criteria": {
      "has_minecart": "2022-09-30 04:14:17 -0600"
    },
    "done": true
  },
  "minecraft:recipes/combat/golden_sword": {
    "criteria": {
      "has_gold_ingot": "2022-09-30 04:52:58 -0600"
    },
    "done": true
  },
  "minecraft:recipes/building_blocks/brown_concrete_powder": {
    "criteria": {
      "has_sand": "2022-09-28 03:49:33 -0600"
    },
    "done": true
  },
  "minecraft:recipes/building_blocks/iron_block": {
    "criteria": {
      "has_iron_ingot": "2022-09-27 11:50:25 -0600"
    },
    "done": true
  },
  "minecraft:recipes/transportation/mangrove_boat": {
    "criteria": {
      "in_water": "2022-09-27 11:33:24 -0600"
    },
    "done": true
  },
  "minecraft:recipes/tools/wooden_shovel": {
    "criteria": {
      "has_stick": "2022-09-27 15:00:37 -0600"
    },
    "done": true
  },
  "minecraft:recipes/misc/red_dye_from_poppy": {
    "criteria": {
      "has_poppy": "2022-09-30 04:53:26 -0600"
    },
    "done": true
  },
  "minecraft:recipes/combat/diamond_sword": {
    "criteria": {
      "has_diamond": "2022-09-27 11:33:33 -0600"
    },
    "done": true
  },
  "minecraft:recipes/tools/shears": {
    "criteria": {
      "has_iron_ingot": "2022-09-27 11:50:25 -0600"
    },
    "done": true
  },
  "minecraft:recipes/building_blocks/coal_block": {
    "criteria": {
      "has_coal": "2022-09-30 04:52:56 -0600"
    },
    "done": true
  },
  "minecraft:recipes/misc/yellow_dye_from_dandelion": {
    "criteria": {
      "has_dandelion": "2022-09-30 04:53:26 -0600"
    },
    "done": true
  },
  "minecraft:recipes/transportation/spruce_boat": {
    "criteria": {
      "in_water": "2022-09-27 11:33:24 -0600"
    },
    "done": true
  },
  "minecraft:recipes/decorations/jukebox": {
    "criteria": {
      "has_diamond": "2022-09-27 11:33:33 -0600"
    },
    "done": true
  },
  "minecraft:recipes/redstone/light_weighted_pressure_plate": {
    "criteria": {
      "has_gold_ingot": "2022-09-30 04:52:58 -0600"
    },
    "done": true
  },
  "minecraft:recipes/misc/flower_banner_pattern": {
    "criteria": {
      "has_oxeye_daisy": "2022-09-30 04:53:27 -0600"
    },
    "done": true
  },
  "minecraft:recipes/combat/wooden_sword": {
    "criteria": {
      "has_stick": "2022-09-27 15:00:37 -0600"
    },
    "done": true
  },
  "minecraft:recipes/misc/red_dye_from_beetroot": {
    "criteria": {
      "has_beetroot": "2022-09-30 04:53:27 -0600"
    },
    "done": true
  },
  "minecraft:recipes/misc/firework_rocket_simple": {
    "criteria": {
      "has_gunpowder": "2022-09-30 04:54:57 -0600"
    },
    "done": true
  },
  "minecraft:recipes/building_blocks/blue_concrete_powder": {
    "criteria": {
      "has_sand": "2022-09-28 03:49:33 -0600"
    },
    "done": true
  },
  "minecraft:recipes/building_blocks/gray_concrete_powder": {
    "criteria": {
      "has_sand": "2022-09-28 03:49:33 -0600"
    },
    "done": true
  },
  "minecraft:recipes/misc/conduit": {
    "criteria": {
      "has_nautilus_shell": "2022-09-27 12:53:10 -0600"
    },
    "done": true
  },
  "minecraft:recipes/building_blocks/emerald_block": {
    "criteria": {
      "has_emerald": "2022-09-28 03:36:14 -0600"
    },
    "done": true
  },
  "minecraft:recipes/misc/gold_nugget": {
    "criteria": {
      "has_gold_ingot": "2022-09-30 04:52:58 -0600"
    },
    "done": true
  },
  "minecraft:recipes/misc/sugar_from_sugar_cane": {
    "criteria": {
      "has_sugar_cane": "2022-09-30 04:53:26 -0600"
    },
    "done": true
  },
  "minecraft:recipes/combat/iron_leggings": {
    "criteria": {
      "has_iron_ingot": "2022-09-27 11:50:25 -0600"
    },
    "done": true
  },
  "minecraft:recipes/tools/golden_axe": {
    "criteria": {
      "has_gold_ingot": "2022-09-30 04:52:58 -0600"
    },
    "done": true
  },
  "minecraft:recipes/tools/iron_axe": {
    "criteria": {
      "has_iron_ingot": "2022-09-27 11:50:25 -0600"
    },
    "done": true
  },
  "minecraft:recipes/tools/wooden_hoe": {
    "criteria": {
      "has_stick": "2022-09-27 15:00:37 -0600"
    },
    "done": true
  },
  "minecraft:recipes/combat/shield": {
    "criteria": {
      "has_iron_ingot": "2022-09-27 11:50:25 -0600"
    },
    "done": true
  },
  "minecraft:recipes/building_blocks/sea_lantern": {
    "criteria": {
      "has_prismarine_crystals": "2022-09-30 04:54:57 -0600"
    },
    "done": true
  },
  "minecraft:recipes/combat/golden_helmet": {
    "criteria": {
      "has_gold_ingot": "2022-09-30 04:52:58 -0600"
    },
    "done": true
  },
  "minecraft:recipes/tools/lead": {
    "criteria": {
      "has_slime_ball": "2022-09-30 04:54:57 -0600"
    },
    "done": true
  },
  "minecraft:recipes/food/cooked_cod": {
    "criteria": {
      "has_cod": "2022-09-27 11:03:15 -0600"
    },
    "done": true
  },
  "minecraft:recipes/misc/bucket": {
    "criteria": {
      "has_iron_ingot": "2022-09-27 11:50:25 -0600"
    },
    "done": true
  },
  "minecraft:recipes/redstone/tripwire_hook": {
    "criteria": {
      "has_string": "2022-09-30 04:14:21 -0600"
    },
    "done": true
  },
  "minecraft:recipes/combat/iron_boots": {
    "criteria": {
      "has_iron_ingot": "2022-09-27 11:50:25 -0600"
    },
    "done": true
  },
  "minecraft:recipes/redstone/hopper": {
    "criteria": {
      "has_iron_ingot": "2022-09-27 11:50:25 -0600"
    },
    "done": true
  },
  "minecraft:recipes/building_blocks/black_concrete_powder": {
    "criteria": {
      "has_sand": "2022-09-28 03:49:33 -0600"
    },
    "done": true
  },
  "minecraft:recipes/redstone/note_block": {
    "criteria": {
      "has_redstone": "2022-09-30 04:14:19 -0600"
    },
    "done": true
  },
  "minecraft:recipes/food/cooked_salmon": {
    "criteria": {
      "has_salmon": "2022-09-27 11:33:33 -0600"
    },
    "done": true
  },
  "minecraft:recipes/combat/iron_chestplate": {
    "criteria": {
      "has_iron_ingot": "2022-09-27 11:50:25 -0600"
    },
    "done": true
  },
  "minecraft:recipes/combat/crossbow": {
    "criteria": {
      "has_iron_ingot": "2022-09-27 11:50:25 -0600"
    },
    "done": true
  },
  "minecraft:recipes/redstone/dropper": {
    "criteria": {
      "has_redstone": "2022-09-30 04:14:19 -0600"
    },
    "done": true
  },
  "minecraft:recipes/building_blocks/light_gray_concrete_powder": {
    "criteria": {
      "has_sand": "2022-09-28 03:49:33 -0600"
    },
    "done": true
  },
  "minecraft:recipes/building_blocks/light_blue_concrete_powder": {
    "criteria": {
      "has_sand": "2022-09-28 03:49:33 -0600"
    },
    "done": true
  },
  "minecraft:recipes/building_blocks/prismarine_bricks": {
    "criteria": {
      "has_prismarine_shard": "2022-09-30 04:54:58 -0600"
    },
    "done": true
  },
  "minecraft:recipes/misc/leather_horse_armor": {
    "criteria": {
      "has_leather": "2022-09-27 15:31:59 -0600"
    },
    "done": true
  },
  "minecraft:recipes/combat/leather_leggings": {
    "criteria": {
      "has_leather": "2022-09-27 15:31:59 -0600"
    },
    "done": true
  },
  "minecraft:recipes/building_blocks/glass": {
    "criteria": {
      "has_sand": "2022-09-28 03:49:33 -0600"
    },
    "done": true
  },
  "minecraft:recipes/combat/iron_helmet": {
    "criteria": {
      "has_iron_ingot": "2022-09-27 11:50:25 -0600"
    },
    "done": true
  },
  "minecraft:recipes/tools/golden_shovel": {
    "criteria": {
      "has_gold_ingot": "2022-09-30 04:52:58 -0600"
    },
    "done": true
  },
  "minecraft:recipes/building_blocks/pink_concrete_powder": {
    "criteria": {
      "has_sand": "2022-09-28 03:49:33 -0600"
    },
    "done": true
  },
  "minecraft:recipes/building_blocks/red_concrete_powder": {
    "criteria": {
      "has_sand": "2022-09-28 03:49:33 -0600"
    },
    "done": true
  },
  "minecraft:recipes/combat/bow": {
    "criteria": {
      "has_string": "2022-09-30 04:14:21 -0600"
    },
    "done": true
  },
  "minecraft:recipes/redstone/tnt": {
    "criteria": {
      "has_gunpowder": "2022-09-30 04:54:57 -0600"
    },
    "done": true
  },
  "minecraft:recipes/combat/leather_chestplate": {
    "criteria": {
      "has_leather": "2022-09-27 15:31:59 -0600"
    },
    "done": true
  },
  "minecraft:recipes/building_blocks/purple_concrete_powder": {
    "criteria": {
      "has_sand": "2022-09-28 03:49:33 -0600"
    },
    "done": true
  },
  "minecraft:recipes/tools/compass": {
    "criteria": {
      "has_redstone": "2022-09-30 04:14:19 -0600"
    },
    "done": true
  },
  "minecraft:recipes/decorations/iron_bars": {
    "criteria": {
      "has_iron_ingot": "2022-09-27 11:50:25 -0600"
    },
    "done": true
  },
  "minecraft:recipes/tools/golden_pickaxe": {
    "criteria": {
      "has_gold_ingot": "2022-09-30 04:52:58 -0600"
    },
    "done": true
  },
  "minecraft:recipes/misc/red_dye_from_rose_bush": {
    "criteria": {
      "has_rose_bush": "2022-09-30 04:53:28 -0600"
    },
    "done": true
  },
  "minecraft:recipes/building_blocks/gold_block": {
    "criteria": {
      "has_gold_ingot": "2022-09-30 04:52:58 -0600"
    },
    "done": true
  },
  "minecraft:recipes/combat/diamond_chestplate": {
    "criteria": {
      "has_diamond": "2022-09-27 11:33:33 -0600"
    },
    "done": true
  },
  "minecraft:recipes/redstone/sticky_piston": {
    "criteria": {
      "has_slime_ball": "2022-09-30 04:54:57 -0600"
    },
    "done": true
  },
  "minecraft:recipes/redstone/target": {
    "criteria": {
      "has_redstone": "2022-09-30 04:14:19 -0600"
    },
    "done": true
  },
  "minecraft:recipes/transportation/minecart": {
    "criteria": {
      "has_iron_ingot": "2022-09-27 11:50:25 -0600"
    },
    "done": true
  },
  "minecraft:recipes/misc/yellow_dye_from_sunflower": {
    "criteria": {
      "has_sunflower": "2022-09-30 04:54:14 -0600"
    },
    "done": true
  },
  "minecraft:recipes/food/beetroot_soup": {
    "criteria": {
      "has_beetroot": "2022-09-30 04:53:27 -0600"
    },
    "done": true
  },
  "minecraft:adventure/adventuring_time": {
    "criteria": {
      "minecraft:river": "2022-09-27 13:21:21 -0600",
      "minecraft:desert": "2022-09-27 11:02:26 -0600"
    },
    "done": false
  },
  "minecraft:recipes/redstone/iron_door": {
    "criteria": {
      "has_iron_ingot": "2022-09-27 11:50:25 -0600"
    },
    "done": true
  },
  "minecraft:recipes/transportation/chest_minecart": {
    "criteria": {
      "has_minecart": "2022-09-30 04:14:17 -0600"
    },
    "done": true
  },
  "minecraft:recipes/combat/diamond_leggings": {
    "criteria": {
      "has_diamond": "2022-09-27 11:33:33 -0600"
    },
    "done": true
  },
  "minecraft:recipes/building_blocks/sandstone": {
    "criteria": {
      "has_sand": "2022-09-28 03:49:33 -0600"
    },
    "done": true
  },
  "minecraft:recipes/tools/iron_hoe": {
    "criteria": {
      "has_iron_ingot": "2022-09-27 11:50:25 -0600"
    },
    "done": true
  },
  "minecraft:recipes/tools/wooden_pickaxe": {
    "criteria": {
      "has_stick": "2022-09-27 15:00:37 -0600"
    },
    "done": true
  },
  "minecraft:recipes/redstone/redstone_torch": {
    "criteria": {
      "has_redstone": "2022-09-30 04:14:19 -0600"
    },
    "done": true
  },
  "minecraft:recipes/transportation/birch_boat": {
    "criteria": {
      "in_water": "2022-09-27 11:33:24 -0600"
    },
    "done": true
  },
  "minecraft:recipes/food/golden_apple": {
    "criteria": {
      "has_gold_ingot": "2022-09-30 04:52:58 -0600"
    },
    "done": true
  },
  "minecraft:recipes/misc/magenta_dye_from_allium": {
    "criteria": {
      "has_allium": "2022-09-30 04:53:25 -0600"
    },
    "done": true
  },
  "minecraft:recipes/building_blocks/green_concrete_powder": {
    "criteria": {
      "has_sand": "2022-09-28 03:49:33 -0600"
    },
    "done": true
  },
  "minecraft:recipes/transportation/acacia_boat": {
    "criteria": {
      "in_water": "2022-09-27 11:33:24 -0600"
    },
    "done": true
  },
  "minecraft:recipes/tools/iron_shovel": {
    "criteria": {
      "has_iron_ingot": "2022-09-27 11:50:25 -0600"
    },
    "done": true
  },
  "minecraft:recipes/redstone/iron_trapdoor": {
    "criteria": {
      "has_iron_ingot": "2022-09-27 11:50:25 -0600"
    },
    "done": true
  },
  "minecraft:recipes/decorations/smithing_table": {
    "criteria": {
      "has_iron_ingot": "2022-09-27 11:50:25 -0600"
    },
    "done": true
  },
  "minecraft:recipes/combat/leather_boots": {
    "criteria": {
      "has_leather": "2022-09-27 15:31:59 -0600"
    },
    "done": true
  },
  "minecraft:recipes/transportation/jungle_boat": {
    "criteria": {
      "in_water": "2022-09-27 11:33:24 -0600"
    },
    "done": true
  },
  "minecraft:recipes/misc/red_dye_from_tulip": {
    "criteria": {
      "has_red_flower": "2022-09-30 04:53:27 -0600"
    },
    "done": true
  },
  "minecraft:recipes/food/cooked_salmon_from_campfire_cooking": {
    "criteria": {
      "has_salmon": "2022-09-27 11:33:33 -0600"
    },
    "done": true
  },
  "minecraft:recipes/misc/iron_ingot_from_iron_block": {
    "criteria": {
      "has_iron_block": "2022-09-29 08:03:00 -0600"
    },
    "done": true
  },
  "minecraft:recipes/building_blocks/white_concrete_powder": {
    "criteria": {
      "has_sand": "2022-09-28 03:49:33 -0600"
    },
    "done": true
  },
  "minecraft:recipes/misc/orange_dye_from_orange_tulip": {
    "criteria": {
      "has_orange_tulip": "2022-09-30 04:53:26 -0600"
    },
    "done": true
  },
  "minecraft:recipes/decorations/item_frame": {
    "criteria": {
      "has_leather": "2022-09-27 15:31:59 -0600"
    },
    "done": true
  },
  "minecraft:recipes/building_blocks/diamond_block": {
    "criteria": {
      "has_diamond": "2022-09-27 11:33:33 -0600"
    },
    "done": true
  },
  "minecraft:recipes/redstone/heavy_weighted_pressure_plate": {
    "criteria": {
      "has_iron_ingot": "2022-09-27 11:50:25 -0600"
    },
    "done": true
  },
  "minecraft:recipes/tools/clock": {
    "criteria": {
      "has_redstone": "2022-09-30 04:14:19 -0600"
    },
    "done": true
  },
  "minecraft:recipes/building_blocks/white_wool_from_string": {
    "criteria": {
      "has_string": "2022-09-30 04:14:21 -0600"
    },
    "done": true
  },
  "minecraft:recipes/transportation/dark_oak_boat": {
    "criteria": {
      "in_water": "2022-09-27 11:33:24 -0600"
    },
    "done": true
  },
  "minecraft:recipes/food/pumpkin_pie": {
    "criteria": {
      "has_pumpkin": "2022-09-30 04:53:26 -0600"
    },
    "done": true
  },
  "minecraft:recipes/transportation/carrot_on_a_stick": {
    "criteria": {
      "has_carrot": "2022-09-30 04:53:26 -0600"
    },
    "done": true
  },
  "minecraft:recipes/tools/diamond_pickaxe": {
    "criteria": {
      "has_diamond": "2022-09-27 11:33:33 -0600"
    },
    "done": true
  },
  "minecraft:recipes/tools/diamond_hoe": {
    "criteria": {
      "has_diamond": "2022-09-27 11:33:33 -0600"
    },
    "done": true
  },
  "minecraft:recipes/food/baked_potato_from_smoking": {
    "criteria": {
      "has_potato": "2022-09-30 04:54:14 -0600"
    },
    "done": true
  },
  "minecraft:recipes/redstone/lightning_rod": {
    "criteria": {
      "has_copper_ingot": "2022-09-28 03:39:35 -0600"
    },
    "done": true
  },
  "minecraft:husbandry/fishy_business": {
    "criteria": {
      "cod": "2022-09-27 11:03:15 -0600"
    },
    "done": true
  },
  "minecraft:recipes/tools/diamond_shovel": {
    "criteria": {
      "has_diamond": "2022-09-27 11:33:33 -0600"
    },
    "done": true
  },
  "minecraft:recipes/building_blocks/lapis_block": {
    "criteria": {
      "has_lapis_lazuli": "2022-09-30 04:52:59 -0600"
    },
    "done": true
  },
  "minecraft:recipes/redstone/redstone_block": {
    "criteria": {
      "has_redstone": "2022-09-30 04:14:19 -0600"
    },
    "done": true
  },
  "minecraft:recipes/transportation/tnt_minecart": {
    "criteria": {
      "has_minecart": "2022-09-30 04:14:17 -0600"
    },
    "done": true
  },
  "minecraft:recipes/food/cooked_cod_from_smoking": {
    "criteria": {
      "has_cod": "2022-09-27 11:03:15 -0600"
    },
    "done": true
  },
  "minecraft:recipes/redstone/piston": {
    "criteria": {
      "has_redstone": "2022-09-30 04:14:19 -0600"
    },
    "done": true
  },
  "minecraft:recipes/combat/golden_leggings": {
    "criteria": {
      "has_gold_ingot": "2022-09-30 04:52:58 -0600"
    },
    "done": true
  },
  "minecraft:recipes/food/baked_potato": {
    "criteria": {
      "has_potato": "2022-09-30 04:54:14 -0600"
    },
    "done": true
  },
  "minecraft:recipes/decorations/lantern": {
    "criteria": {
      "has_iron_ingot": "2022-09-27 11:50:25 -0600"
    },
    "done": true
  },
  "minecraft:recipes/misc/light_gray_dye_from_azure_bluet": {
    "criteria": {
      "has_azure_bluet": "2022-09-30 04:53:26 -0600"
    },
    "done": true
  },
  "minecraft:recipes/misc/stick_from_bamboo_item": {
    "criteria": {
      "has_bamboo": "2022-09-30 04:53:25 -0600"
    },
    "done": true
  },
  "minecraft:recipes/transportation/rail": {
    "criteria": {
      "has_minecart": "2022-09-30 04:14:17 -0600"
    },
    "done": true
  },
  "minecraft:recipes/building_blocks/prismarine": {
    "criteria": {
      "has_prismarine_shard": "2022-09-30 04:54:58 -0600"
    },
    "done": true
  },
  "minecraft:recipes/decorations/chain": {
    "criteria": {
      "has_iron_ingot": "2022-09-27 11:50:25 -0600"
    },
    "done": true
  },
  "minecraft:recipes/combat/diamond_boots": {
    "criteria": {
      "has_diamond": "2022-09-27 11:33:33 -0600"
    },
    "done": true
  },
  "minecraft:story/mine_diamond": {
    "criteria": {
      "diamond": "2022-09-27 11:33:33 -0600"
    },
    "done": true
  },
  "minecraft:recipes/combat/diamond_helmet": {
    "criteria": {
      "has_diamond": "2022-09-27 11:33:33 -0600"
    },
    "done": true
  },
  "minecraft:recipes/misc/blue_dye": {
    "criteria": {
      "has_lapis_lazuli": "2022-09-30 04:52:59 -0600"
    },
    "done": true
  },
  "minecraft:recipes/misc/light_gray_dye_from_oxeye_daisy": {
    "criteria": {
      "has_oxeye_daisy": "2022-09-30 04:53:27 -0600"
    },
    "done": true
  },
  "minecraft:recipes/transportation/oak_boat": {
    "criteria": {
      "in_water": "2022-09-27 11:33:24 -0600"
    },
    "done": true
  },
  "minecraft:recipes/decorations/soul_campfire": {
    "criteria": {
      "has_stick": "2022-09-27 15:00:37 -0600"
    },
    "done": true
  },
  "minecraft:recipes/food/cooked_cod_from_campfire_cooking": {
    "criteria": {
      "has_cod": "2022-09-27 11:03:15 -0600"
    },
    "done": true
  },
  "minecraft:story/smelt_iron": {
    "criteria": {
      "iron": "2022-09-27 11:50:25 -0600"
    },
    "done": true
  },
  "minecraft:recipes/decorations/anvil": {
    "criteria": {
      "has_iron_block": "2022-09-29 08:03:00 -0600"
    },
    "done": true
  },
  "minecraft:recipes/misc/pink_dye_from_pink_tulip": {
    "criteria": {
      "has_pink_tulip": "2022-09-30 04:53:26 -0600"
    },
    "done": true
  },
  "minecraft:recipes/misc/white_dye_from_lily_of_the_valley": {
    "criteria": {
      "has_lily_of_the_valley": "2022-09-30 04:53:27 -0600"
    },
    "done": true
  },
  "minecraft:recipes/building_blocks/orange_concrete_powder": {
    "criteria": {
      "has_sand": "2022-09-28 03:49:33 -0600"
    },
    "done": true
  },
  "minecraft:recipes/food/baked_potato_from_campfire_cooking": {
    "criteria": {
      "has_potato": "2022-09-30 04:54:14 -0600"
    },
    "done": true
  },
  "minecraft:recipes/building_blocks/cyan_concrete_powder": {
    "criteria": {
      "has_sand": "2022-09-28 03:49:33 -0600"
    },
    "done": true
  },
  "minecraft:recipes/combat/golden_boots": {
    "criteria": {
      "has_gold_ingot": "2022-09-30 04:52:58 -0600"
    },
    "done": true
  },
  "DataVersion": 3120
}